RVCapture/__init__.py
RVCapture/apiManage.py
RVCapture/appConfigs.json
RVCapture/configManage.py
RVCapture/deviceManage.py
RVCapture/dockerManage.py
RVCapture/keysManage.py
RVCapture/main.py
RVCapture/utils.py
rvcapture-0.1.0.dist-info/LICENSE
rvcapture-0.1.0.dist-info/METADATA
rvcapture-0.1.0.dist-info/WHEEL
rvcapture-0.1.0.dist-info/entry_points.txt
rvcapture-0.1.0.dist-info/top_level.txt
rvcapture-0.1.0.dist-info/RECORD
