Metadata-Version: 2.1
Name: rvcapture
Version: 0.1.0
Summary: A CLI tool for RVCapture
Home-page: https://roojh.com
Author: Roojh Health
Author-email: roojh@roojh.com
Classifier: Programming Language :: Python :: 3
Classifier: License :: OSI Approved :: MIT License
Classifier: Operating System :: OS Independent
Requires-Python: >=3.8
License-File: LICENSE
Requires-Dist: certifi==2024.8.30
Requires-Dist: charset-normalizer==3.4.0
Requires-Dist: click==8.1.7
Requires-Dist: colorama==0.4.6
Requires-Dist: halo==0.0.31
Requires-Dist: idna==3.10
Requires-Dist: log-symbols==0.0.14
Requires-Dist: markdown-it-py==3.0.0
Requires-Dist: mdurl==0.1.2
Requires-Dist: pyfiglet==1.0.2
Requires-Dist: Pygments==2.18.0
Requires-Dist: requests==2.32.3
Requires-Dist: rich==13.9.4
Requires-Dist: shellingham==1.5.4
Requires-Dist: six==1.16.0
Requires-Dist: spinners==0.0.24
Requires-Dist: tabulate==0.9.0
Requires-Dist: termcolor==2.5.0
Requires-Dist: typer==0.13.1
Requires-Dist: typing_extensions==4.12.2
Requires-Dist: urllib3==2.2.3
